geosphere/__init__.py
geosphere/geosphere.py
geosphere-0.0.1.dist-info/LICENSE
geosphere-0.0.1.dist-info/METADATA
geosphere-0.0.1.dist-info/WHEEL
geosphere-0.0.1.dist-info/top_level.txt
geosphere-0.0.1.dist-info/RECORD
