Metadata-Version: 2.1
Name: geosphere
Version: 0.0.1
Summary: Spherical geometry utilities for navigation
Home-page: UNKNOWN
Author: Marc Culler
License: GPLv2+
Keywords: spherical,navigation
Platform: UNKNOWN
Classifier: Development Status :: 5 - Production/Stable
Classifier: License :: OSI Approved :: GNU General Public License v2 or later (GPLv2+)
Classifier: Operating System :: OS Independent
Classifier: Programming Language :: Python
License-File: LICENSE
